biomap/__init__.py
biomap/core/__init__.py
biomap/core/database.py
biomap/core/insert.py
biomap/core/mapper.py
biomap_core-0.0.52.data/data/schema/mapper_definition_schema.json
biomap_core-0.0.52.dist-info/LICENSE
biomap_core-0.0.52.dist-info/METADATA
biomap_core-0.0.52.dist-info/WHEEL
biomap_core-0.0.52.dist-info/top_level.txt
biomap_core-0.0.52.dist-info/RECORD
